MANIFEST.in
README.md
VERSION
requirements.txt
setup.cfg
setup.py
rhasspy_profile.egg-info/PKG-INFO
rhasspy_profile.egg-info/SOURCES.txt
rhasspy_profile.egg-info/dependency_links.txt
rhasspy_profile.egg-info/requires.txt
rhasspy_profile.egg-info/top_level.txt
rhasspyprofile/__init__.py
rhasspyprofile/__main__.py
rhasspyprofile/download.py
rhasspyprofile/profile.py
rhasspyprofile/py.typed
rhasspyprofile/profiles/defaults.json
rhasspyprofile/profiles/ca/espeak_phonemes.txt
rhasspyprofile/profiles/ca/frequent_words.txt
rhasspyprofile/profiles/ca/phoneme_examples.txt
rhasspyprofile/profiles/ca/profile.json
rhasspyprofile/profiles/ca/sentences.ini
rhasspyprofile/profiles/ca/stop_words.txt
rhasspyprofile/profiles/ca/slot_programs/rhasspy/number
rhasspyprofile/profiles/ca/slots/rhasspy/days
rhasspyprofile/profiles/ca/slots/rhasspy/months
rhasspyprofile/profiles/cs/frequent_words.txt
rhasspyprofile/profiles/cs/profile.json
rhasspyprofile/profiles/cs/sentences.ini
rhasspyprofile/profiles/cs/stop_words.txt
rhasspyprofile/profiles/cs/kaldi/espeak_phonemes.txt
rhasspyprofile/profiles/cs/kaldi/phoneme_examples.txt
rhasspyprofile/profiles/cs/slot_programs/rhasspy/number
rhasspyprofile/profiles/de/espeak_phonemes.txt
rhasspyprofile/profiles/de/frequent_words.txt
rhasspyprofile/profiles/de/phoneme_examples.txt
rhasspyprofile/profiles/de/profile.json
rhasspyprofile/profiles/de/sentences.ini
rhasspyprofile/profiles/de/stop_words.txt
rhasspyprofile/profiles/de/kaldi/espeak_phonemes.txt
rhasspyprofile/profiles/de/kaldi/phoneme_examples.txt
rhasspyprofile/profiles/de/slot_programs/rhasspy/number
rhasspyprofile/profiles/de/slots/rhasspy/days
rhasspyprofile/profiles/de/slots/rhasspy/months
rhasspyprofile/profiles/el/espeak_phonemes.txt
rhasspyprofile/profiles/el/frequent_words.txt
rhasspyprofile/profiles/el/phoneme_examples.txt
rhasspyprofile/profiles/el/profile.json
rhasspyprofile/profiles/el/sentences.ini
rhasspyprofile/profiles/el/stop_words.txt
rhasspyprofile/profiles/el/slot_programs/rhasspy/number
rhasspyprofile/profiles/el/slots/rhasspy/days
rhasspyprofile/profiles/el/slots/rhasspy/months
rhasspyprofile/profiles/en/espeak_phonemes.txt
